BMI500cao/BMI500clustering.py
BMI500cao/__init__.py
BMI500cao/module1.py
BMI500caonia/BMI500clustering.py
BMI500caonia/__init__.py
BMI500caonia/module1.py
BMI500caonima/BMI500clustering.py
BMI500caonima/__init__.py
BMI500caonima/module1.py
cao/__init__.py
cao/module1.py
examplepy/__init__.py
examplepy/module1.py
BMI500caonia-2.0.0.dist-info/LICENSE
BMI500caonia-2.0.0.dist-info/METADATA
BMI500caonia-2.0.0.dist-info/WHEEL
BMI500caonia-2.0.0.dist-info/top_level.txt
BMI500caonia-2.0.0.dist-info/RECORD
